odoo/addons/shopfloor_single_product_transfer/README.rst
odoo/addons/shopfloor_single_product_transfer/__init__.py
odoo/addons/shopfloor_single_product_transfer/__manifest__.py
odoo/addons/shopfloor_single_product_transfer/hooks.py
odoo/addons/shopfloor_single_product_transfer/data/shopfloor_scenario_data.xml
odoo/addons/shopfloor_single_product_transfer/demo/shopfloor_menu_demo.xml
odoo/addons/shopfloor_single_product_transfer/demo/stock_picking_type_demo.xml
odoo/addons/shopfloor_single_product_transfer/docs/diagram.plantuml
odoo/addons/shopfloor_single_product_transfer/docs/diagram.png
odoo/addons/shopfloor_single_product_transfer/docs/oca_logo.png
odoo/addons/shopfloor_single_product_transfer/i18n/it.po
odoo/addons/shopfloor_single_product_transfer/i18n/shopfloor_single_product_transfer.pot
odoo/addons/shopfloor_single_product_transfer/migrations/14.0.1.1.0/post-migrate.py
odoo/addons/shopfloor_single_product_transfer/readme/CONTRIBUTORS.rst
odoo/addons/shopfloor_single_product_transfer/readme/DESCRIPTION.rst
odoo/addons/shopfloor_single_product_transfer/readme/USAGE.rst
odoo/addons/shopfloor_single_product_transfer/services/__init__.py
odoo/addons/shopfloor_single_product_transfer/services/single_product_transfer.py
odoo/addons/shopfloor_single_product_transfer/static/description/icon.png
odoo/addons/shopfloor_single_product_transfer/static/description/index.html
odoo/addons/shopfloor_single_product_transfer/tests/__init__.py
odoo/addons/shopfloor_single_product_transfer/tests/common.py
odoo/addons/shopfloor_single_product_transfer/tests/test_scan_location_or_package.py
odoo/addons/shopfloor_single_product_transfer/tests/test_scan_product.py
odoo/addons/shopfloor_single_product_transfer/tests/test_set_location.py
odoo/addons/shopfloor_single_product_transfer/tests/test_set_quantity.py
odoo/addons/shopfloor_single_product_transfer/tests/test_set_quantity_checkout_sync.py
odoo/addons/shopfloor_single_product_transfer/tests/test_start.py
odoo14_addon_shopfloor_single_product_transfer-14.0.2.5.0.dist-info/METADATA
odoo14_addon_shopfloor_single_product_transfer-14.0.2.5.0.dist-info/WHEEL
odoo14_addon_shopfloor_single_product_transfer-14.0.2.5.0.dist-info/top_level.txt
odoo14_addon_shopfloor_single_product_transfer-14.0.2.5.0.dist-info/RECORD
